lambda_happy/__init__.py
lambda_happy/dependency_utils.py
lambda_happy/lambda_happy.py
lambda_happy/lib_lambda.cpython-310-x86_64-linux-gnu.so
lambda_happy_benchmark/__init__.py
lambda_happy_benchmark/benchmark.py
lambda_happy_benchmark/dependencies.py
lambda_happy_benchmark/lambda_happy_partial.py
lambda_happy_validation/__init__.py
lambda_happy_validation/dependencies.py
lambda_happy_validation/ista_solver.py
lambda_happy_validation/validation.py
scripts/run_benchmark.py
scripts/run_validation.py
scripts/utils.py
lambda_happy-0.1.13.dist-info/METADATA
lambda_happy-0.1.13.dist-info/WHEEL
lambda_happy-0.1.13.dist-info/entry_points.txt
lambda_happy-0.1.13.dist-info/top_level.txt
lambda_happy-0.1.13.dist-info/RECORD
